supersed/__init__.py
supersed/supersed.py
supersed-0.3.8.dist-info/LICENSE
supersed-0.3.8.dist-info/METADATA
supersed-0.3.8.dist-info/WHEEL
supersed-0.3.8.dist-info/entry_points.txt
supersed-0.3.8.dist-info/top_level.txt
supersed-0.3.8.dist-info/RECORD
