Metadata-Version: 2.1
Name: supersed
Version: 0.3.8
Summary: An LLM powered super CLI
Author-email: Anubhab Chakraborty <anuv@akcanuv.com>
License: MIT
Project-URL: homepage, https://github.com/akcanuv/supersed
Classifier: Programming Language :: Python :: 3
Classifier: License :: OSI Approved :: MIT License
Classifier: Operating System :: OS Independent
Requires-Python: >=3.6
License-File: LICENSE
Requires-Dist: openai>=1.53.0
